LICENSE
README.md
pyproject.toml
hpoglue/__init__.py
hpoglue/_run.py
hpoglue/benchmark.py
hpoglue/budget.py
hpoglue/config.py
hpoglue/constants.py
hpoglue/dataframe_utils.py
hpoglue/env.py
hpoglue/fidelity.py
hpoglue/measure.py
hpoglue/optimizer.py
hpoglue/problem.py
hpoglue/query.py
hpoglue/result.py
hpoglue/run_glue.py
hpoglue/utils.py
hpoglue.egg-info/PKG-INFO
hpoglue.egg-info/SOURCES.txt
hpoglue.egg-info/dependency_links.txt
hpoglue.egg-info/requires.txt
hpoglue.egg-info/top_level.txt