Metadata-Version: 2.4
Name: hpoglue
Version: 0.2.5
Summary: HPO tool with a modular API that allows for the easy interfacing of a new Optimizer and a new Benchmark
Author-email: Soham Basu <soham.basu07@gmail.com>, Eddie Bergman <eddiebergmanhs@gmail.com>, Neeratyoy Malik <neeratyoy@gmail.com>
License: BSD 3-Clause License
Project-URL: source, https://github.com/automl/hpoglue/
Classifier: Intended Audience :: Science/Research
Classifier: Intended Audience :: Developers
Classifier: License :: OSI Approved :: BSD License
Classifier: Programming Language :: Python
Classifier: Topic :: Software Development
Classifier: Topic :: Scientific/Engineering
Classifier: Operating System :: POSIX
Classifier: Operating System :: Unix
Classifier: Operating System :: MacOS
Classifier: Programming Language :: Python :: 3
Classifier: Programming Language :: Python :: 3.10
Requires-Python: >=3.10
License-File: LICENSE
Requires-Dist: numpy
Requires-Dist: pandas<3,>=2
Requires-Dist: tqdm
Requires-Dist: more_itertools
Requires-Dist: ConfigSpace>=1.0
Provides-Extra: dev
Requires-Dist: ruff; extra == "dev"
Requires-Dist: mypy; extra == "dev"
Requires-Dist: pre-commit; extra == "dev"
Provides-Extra: notebook
Requires-Dist: ipykernel; extra == "notebook"
Dynamic: license-file
